SpinPyToolBox/__init__.py
SpinPyToolBox/spinlib.py
SpinPyToolBox-1.0.dist-info/METADATA
SpinPyToolBox-1.0.dist-info/WHEEL
SpinPyToolBox-1.0.dist-info/top_level.txt
SpinPyToolBox-1.0.dist-info/RECORD
