Metadata-Version: 2.1
Name: SpinPyToolBox
Version: 1.0
Summary: SpinPyToolBox
Home-page: http://github.com/storborg/SpinPyToolBox
Author: HeavenMu
Author-email: muheaven@outlook.com
License: MIT
Platform: UNKNOWN
